{"type": "FeatureCollection", "features": [{"type": "Feature", "geometry": {"type": "Point", "coordinates": [121.36694691071567, 31.21085065113977]}, "properties": {"name": "\u4e1c\u6cf0\u7965\u751f\u714e\u9986(\u767e\u8054\u897f\u90ca\u8d2d\u7269\u4e2d\u5fc3)", "biz": "050116 \u9910\u996e\u670d\u52a1;\u4e2d\u9910\u5385;\u8001\u5b57\u53f7", "pty": "0501"}}, {"type": "Feature", "geometry": {"type": "Point", "coordinates": [121.44557273735714, 31.24764449522949]}, "properties": {"name": "\u5168\u805a\u5fb7(\u95f8\u5317\u5e97)", "biz": "050111|050116 \u9910\u996e\u670d\u52a1;\u4e2d\u9910\u5385;\u5317\u4eac\u83dc|\u9910\u996e\u670d\u52a1;\u4e2d\u9910\u5385;\u8001\u5b57\u53f7", "pty": "0501"}}, {"type": "Feature", "geometry": {"type": "Point", "coordinates": [121.44557273735714, 31.24764449522949]}, "properties": {"name": "\u5168\u805a\u5fb7(\u95f8\u5317\u5e97)", "biz": "050111|050116 \u9910\u996e\u670d\u52a1;\u4e2d\u9910\u5385;\u5317\u4eac\u83dc|\u9910\u996e\u670d\u52a1;\u4e2d\u9910\u5385;\u8001\u5b57\u53f7", "pty": "0501"}}, {"type": "Feature", "geometry": {"type": "Point", "coordinates": [121.39938267222067, 31.277959081242916]}, "properties": {"name": "\u719f\u98df\u5916\u5356", "biz": "050116 \u9910\u996e\u670d\u52a1;\u4e2d\u9910\u5385;\u8001\u5b57\u53f7", "pty": "0501"}}, {"type": "Feature", "geometry": {"type": "Point", "coordinates": [121.53938791085142, 31.28851260827627]}, "properties": {"name": "\u4e2d\u534e\u8001\u5b57\u53f7", "biz": "050116 \u9910\u996e\u670d\u52a1;\u4e2d\u9910\u5385;\u8001\u5b57\u53f7", "pty": "0501"}}, {"type": "Feature", "geometry": {"type": "Point", "coordinates": [121.35939204638082, 31.101388702621264]}, "properties": {"name": "\u4e94\u82b3\u658b(\u8398\u677e\u8def\u5e97)", "biz": "050116 \u9910\u996e\u670d\u52a1;\u4e2d\u9910\u5385;\u8001\u5b57\u53f7", "pty": "0501"}}, {"type": "Feature", "geometry": {"type": "Point", "coordinates": [121.57704962410604, 31.253340186820587]}, "properties": {"name": "\u4e2d\u534e\u8001\u5b57\u53f7", "biz": "050116 \u9910\u996e\u670d\u52a1;\u4e2d\u9910\u5385;\u8001\u5b57\u53f7", "pty": "0501"}}, {"type": "Feature", "geometry": {"type": "Point", "coordinates": [121.4980892728486, 31.239127331559555]}, "properties": {"name": "\u9f0e\u6cf0\u4e30(\u56fd\u91d1\u4e2d\u5fc3\u5546\u573a)", "biz": "050122|050116 \u9910\u996e\u670d\u52a1;\u4e2d\u9910\u5385;\u53f0\u6e7e\u83dc|\u9910\u996e\u670d\u52a1;\u4e2d\u9910\u5385;\u8001\u5b57\u53f7", "pty": "0501"}}, {"type": "Feature", "geometry": {"type": "Point", "coordinates": [121.4980892728486, 31.239127331559555]}, "properties": {"name": "\u9f0e\u6cf0\u4e30(\u56fd\u91d1\u4e2d\u5fc3\u5546\u573a)", "biz": "050122|050116 \u9910\u996e\u670d\u52a1;\u4e2d\u9910\u5385;\u53f0\u6e7e\u83dc|\u9910\u996e\u670d\u52a1;\u4e2d\u9910\u5385;\u8001\u5b57\u53f7", "pty": "0501"}}, {"type": "Feature", "geometry": {"type": "Point", "coordinates": [121.33168493139853, 30.748511387723376]}, "properties": {"name": "\u4e94\u82b3\u658b(\u8499\u5c71\u5317\u8def\u5e97)", "biz": "050116 \u9910\u996e\u670d\u52a1;\u4e2d\u9910\u5385;\u8001\u5b57\u53f7", "pty": "0501"}}, {"type": "Feature", "geometry": {"type": "Point", "coordinates": [121.27288970185604, 31.176415554360016]}, "properties": {"name": "\u65b0\u5ddd\u798f\u706b\u9505(\u76c8\u6e2f\u4e1c\u8def\u5e97)", "biz": "050116 \u9910\u996e\u670d\u52a1;\u4e2d\u9910\u5385;\u8001\u5b57\u53f7", "pty": "0501"}}]}