{"type": "FeatureCollection", "features": [{"type": "Feature", "geometry": {"type": "Point", "coordinates": [121.4083592128929, 31.11160123561056]}, "properties": {"name": "\u6211\u7231\u6211\u5bb6(\u8398\u6f6e\u5bb6\u5177\u6625\u6f6e\u8defB\u9986)", "biz": "060602|071600 \u8d2d\u7269\u670d\u52a1;\u5bb6\u5c45\u5efa\u6750\u5e02\u573a;\u5bb6\u5177\u57ce|\u751f\u6d3b\u670d\u52a1;\u4e2d\u4ecb\u673a\u6784;\u4e2d\u4ecb\u673a\u6784", "pty": "0606"}}, {"type": "Feature", "geometry": {"type": "Point", "coordinates": [121.4083592128929, 31.11160123561056]}, "properties": {"name": "\u6211\u7231\u6211\u5bb6(\u8398\u6f6e\u5bb6\u5177\u6625\u6f6e\u8defB\u9986)", "biz": "060602|071600 \u8d2d\u7269\u670d\u52a1;\u5bb6\u5c45\u5efa\u6750\u5e02\u573a;\u5bb6\u5177\u57ce|\u751f\u6d3b\u670d\u52a1;\u4e2d\u4ecb\u673a\u6784;\u4e2d\u4ecb\u673a\u6784", "pty": "0606"}}]}