{"type": "FeatureCollection", "features": [{"type": "Feature", "geometry": {"type": "Point", "coordinates": [121.3428825438339, 31.19236821690736]}, "properties": {"name": "\u65e5\u4e0a\u514d\u7a0e\u884c(\u8679\u6865\u673a\u573a\u5e97)", "biz": "060103 \u8d2d\u7269\u670d\u52a1;\u5546\u573a;\u514d\u7a0e\u54c1\u5e97", "pty": "0601"}}, {"type": "Feature", "geometry": {"type": "Point", "coordinates": [121.42382209901311, 31.231486718780396]}, "properties": {"name": "\u4e2d\u670d\u514d\u7a0e(\u60a6\u8fbe889\u5e7f\u573a)", "biz": "060103 \u8d2d\u7269\u670d\u52a1;\u5546\u573a;\u514d\u7a0e\u54c1\u5e97", "pty": "0601"}}, {"type": "Feature", "geometry": {"type": "Point", "coordinates": [121.77310677234186, 31.135713274317208]}, "properties": {"name": "\u65e5\u4e0a\u514d\u7a0e\u5e97(\u81ea\u8d38\u533a\u5e97)", "biz": "060103 \u8d2d\u7269\u670d\u52a1;\u5546\u573a;\u514d\u7a0e\u54c1\u5e97", "pty": "0601"}}, {"type": "Feature", "geometry": {"type": "Point", "coordinates": [121.80581303105481, 31.15317634402237]}, "properties": {"name": "\u65e5\u4e0a\u514d\u7a0e\u70df\u9152\u5e97(\u4e0a\u6d77\u6d66\u4e1c\u56fd\u9645\u673a\u573a)", "biz": "060103 \u8d2d\u7269\u670d\u52a1;\u5546\u573a;\u514d\u7a0e\u54c1\u5e97", "pty": "0601"}}, {"type": "Feature", "geometry": {"type": "Point", "coordinates": [121.60092558576461, 31.320461478282876]}, "properties": {"name": "\u4e0a\u6d77\u4fdd\u7a0e\u5546\u54c1\u4ea4\u6613\u5e02\u573a\u7b2c\u4e00\u5e02\u573a", "biz": "060103 \u8d2d\u7269\u670d\u52a1;\u5546\u573a;\u514d\u7a0e\u54c1\u5e97", "pty": "0601"}}, {"type": "Feature", "geometry": {"type": "Point", "coordinates": [121.7986613438357, 31.15211273620987]}, "properties": {"name": "\u65e5\u4e0a\u514d\u7a0e\u884c(\u6d66\u4e1c\u673a\u573a\u5e97)", "biz": "060103 \u8d2d\u7269\u670d\u52a1;\u5546\u573a;\u514d\u7a0e\u54c1\u5e97", "pty": "0601"}}, {"type": "Feature", "geometry": {"type": "Point", "coordinates": [121.59769652741656, 31.3362415505775]}, "properties": {"name": "\u6bd4\u5229\u53f8(\u8de8\u5883\u514d\u7a0e\u76f4\u8425\u5e97)", "biz": "060103 \u8d2d\u7269\u670d\u52a1;\u5546\u573a;\u514d\u7a0e\u54c1\u5e97", "pty": "0601"}}, {"type": "Feature", "geometry": {"type": "Point", "coordinates": [121.79843107053495, 31.14912393589148]}, "properties": {"name": "\u65e5\u4e0a\u514d\u7a0e\u884c(\u4e0a\u6d77\u6d66\u4e1c\u56fd\u9645\u673a\u573a)", "biz": "060103 \u8d2d\u7269\u670d\u52a1;\u5546\u573a;\u514d\u7a0e\u54c1\u5e97", "pty": "0601"}}, {"type": "Feature", "geometry": {"type": "Point", "coordinates": [121.79827967232552, 31.149782340426306]}, "properties": {"name": "\u65e5\u4e0a\u514d\u7a0e\u884c(\u4e0a\u6d77\u6d66\u4e1c\u56fd\u9645\u673a\u573a)", "biz": "060103 \u8d2d\u7269\u670d\u52a1;\u5546\u573a;\u514d\u7a0e\u54c1\u5e97", "pty": "0601"}}, {"type": "Feature", "geometry": {"type": "Point", "coordinates": [121.7983277814898, 31.149780420056253]}, "properties": {"name": "\u65e5\u4e0a\u514d\u7a0e\u884c(\u4e0a\u6d77\u6d66\u4e1c\u56fd\u9645\u673a\u573a)", "biz": "060103 \u8d2d\u7269\u670d\u52a1;\u5546\u573a;\u514d\u7a0e\u54c1\u5e97", "pty": "0601"}}]}