{"type": "FeatureCollection", "features": [{"type": "Feature", "geometry": {"type": "Point", "coordinates": [121.47683301636347, 31.237885071565046]}, "properties": {"name": "\u5409\u91ce\u5bb6(\u5148\u65bd\u5e97)", "biz": "050309 \u9910\u996e\u670d\u52a1;\u5feb\u9910\u5385;\u5409\u91ce\u5bb6", "pty": "0503"}}, {"type": "Feature", "geometry": {"type": "Point", "coordinates": [121.42338137546518, 31.18674478976516]}, "properties": {"name": "\u5409\u91ce\u5bb6(\u5149\u542f\u57ce)", "biz": "050309 \u9910\u996e\u670d\u52a1;\u5feb\u9910\u5385;\u5409\u91ce\u5bb6", "pty": "0503"}}, {"type": "Feature", "geometry": {"type": "Point", "coordinates": [121.42505241173313, 31.155965535086814]}, "properties": {"name": "\u5409\u91ce\u5bb6(\u4e0a\u6d77\u5357\u7ad9\u67f3\u5dde\u8def\u5e97)", "biz": "050309 \u9910\u996e\u670d\u52a1;\u5feb\u9910\u5385;\u5409\u91ce\u5bb6", "pty": "0503"}}, {"type": "Feature", "geometry": {"type": "Point", "coordinates": [121.52591715288159, 31.208674289375228]}, "properties": {"name": "\u5409\u91ce\u5bb6(\u6768\u9ad8\u5e97)", "biz": "050309 \u9910\u996e\u670d\u52a1;\u5feb\u9910\u5385;\u5409\u91ce\u5bb6", "pty": "0503"}}, {"type": "Feature", "geometry": {"type": "Point", "coordinates": [121.51470694192167, 31.230510160530027]}, "properties": {"name": "\u5409\u91ce\u5bb6(\u6d66\u4e1c\u98df\u54c1\u57ce\u5e97)", "biz": "050309 \u9910\u996e\u670d\u52a1;\u5feb\u9910\u5385;\u5409\u91ce\u5bb6", "pty": "0503"}}, {"type": "Feature", "geometry": {"type": "Point", "coordinates": [121.49891916985898, 31.157357956882507]}, "properties": {"name": "\u5409\u91ce\u5bb6(\u4e0a\u5357\u5e97)", "biz": "050309 \u9910\u996e\u670d\u52a1;\u5feb\u9910\u5385;\u5409\u91ce\u5bb6", "pty": "0503"}}, {"type": "Feature", "geometry": {"type": "Point", "coordinates": [121.58140691611192, 31.202473675198277]}, "properties": {"name": "\u5409\u91ce\u5bb6(\u4f20\u5947\u5e7f\u573a)", "biz": "050309 \u9910\u996e\u670d\u52a1;\u5feb\u9910\u5385;\u5409\u91ce\u5bb6", "pty": "0503"}}]}