{"type": "FeatureCollection", "features": [{"type": "Feature", "geometry": {"type": "Point", "coordinates": [121.47402413187777, 31.25381295452538]}, "properties": {"name": "\u4e0a\u94c1\u56fd\u65c5(\u4e1c\u534e\u8def)", "biz": "070302|070100 \u751f\u6d3b\u670d\u52a1;\u552e\u7968\u5904;\u706b\u8f66\u7968\u4ee3\u552e\u70b9|\u751f\u6d3b\u670d\u52a1;\u65c5\u884c\u793e;\u65c5\u884c\u793e", "pty": "0703"}}, {"type": "Feature", "geometry": {"type": "Point", "coordinates": [121.35414020997341, 31.159468165975095]}, "properties": {"name": "\u706b\u8f66\u7968\u4ee3\u552e\u5904(\u53f7\u4e0a\u897f\u8def)", "biz": "070302|070100 \u751f\u6d3b\u670d\u52a1;\u552e\u7968\u5904;\u706b\u8f66\u7968\u4ee3\u552e\u70b9|\u751f\u6d3b\u670d\u52a1;\u65c5\u884c\u793e;\u65c5\u884c\u793e", "pty": "0703"}}, {"type": "Feature", "geometry": {"type": "Point", "coordinates": [121.47098258975903, 31.235345817340086]}, "properties": {"name": "\u6625\u79cb\u65c5\u6e38", "biz": "070301|070100 \u751f\u6d3b\u670d\u52a1;\u552e\u7968\u5904;\u98de\u673a\u7968\u4ee3\u552e\u70b9|\u751f\u6d3b\u670d\u52a1;\u65c5\u884c\u793e;\u65c5\u884c\u793e", "pty": "0703"}}, {"type": "Feature", "geometry": {"type": "Point", "coordinates": [121.3875837363387, 31.62251990050482]}, "properties": {"name": "\u6df3\u9633\u65c5\u6e38\u822a\u7a7a\u552e\u7968", "biz": "070301|070100 \u751f\u6d3b\u670d\u52a1;\u552e\u7968\u5904;\u98de\u673a\u7968\u4ee3\u552e\u70b9|\u751f\u6d3b\u670d\u52a1;\u65c5\u884c\u793e;\u65c5\u884c\u793e", "pty": "0703"}}, {"type": "Feature", "geometry": {"type": "Point", "coordinates": [121.47402413187777, 31.25381295452538]}, "properties": {"name": "\u4e0a\u94c1\u56fd\u65c5(\u4e1c\u534e\u8def)", "biz": "070302|070100 \u751f\u6d3b\u670d\u52a1;\u552e\u7968\u5904;\u706b\u8f66\u7968\u4ee3\u552e\u70b9|\u751f\u6d3b\u670d\u52a1;\u65c5\u884c\u793e;\u65c5\u884c\u793e", "pty": "0703"}}, {"type": "Feature", "geometry": {"type": "Point", "coordinates": [121.35414020997341, 31.159468165975095]}, "properties": {"name": "\u706b\u8f66\u7968\u4ee3\u552e\u5904(\u53f7\u4e0a\u897f\u8def)", "biz": "070302|070100 \u751f\u6d3b\u670d\u52a1;\u552e\u7968\u5904;\u706b\u8f66\u7968\u4ee3\u552e\u70b9|\u751f\u6d3b\u670d\u52a1;\u65c5\u884c\u793e;\u65c5\u884c\u793e", "pty": "0703"}}, {"type": "Feature", "geometry": {"type": "Point", "coordinates": [121.47098258975903, 31.235345817340086]}, "properties": {"name": "\u6625\u79cb\u65c5\u6e38", "biz": "070301|070100 \u751f\u6d3b\u670d\u52a1;\u552e\u7968\u5904;\u98de\u673a\u7968\u4ee3\u552e\u70b9|\u751f\u6d3b\u670d\u52a1;\u65c5\u884c\u793e;\u65c5\u884c\u793e", "pty": "0703"}}, {"type": "Feature", "geometry": {"type": "Point", "coordinates": [121.3875837363387, 31.62251990050482]}, "properties": {"name": "\u6df3\u9633\u65c5\u6e38\u822a\u7a7a\u552e\u7968", "biz": "070301|070100 \u751f\u6d3b\u670d\u52a1;\u552e\u7968\u5904;\u98de\u673a\u7968\u4ee3\u552e\u70b9|\u751f\u6d3b\u670d\u52a1;\u65c5\u884c\u793e;\u65c5\u884c\u793e", "pty": "0703"}}]}