{"type": "FeatureCollection", "features": [{"type": "Feature", "geometry": {"type": "Point", "coordinates": [121.54263855476857, 31.2186776104602]}, "properties": {"name": "\u4e16\u7eaa\u516c\u56ed-\u516c\u5171\u5395\u6240", "biz": "110106 \u98ce\u666f\u540d\u80dc;\u516c\u56ed\u5e7f\u573a;\u516c\u56ed\u5185\u90e8\u8bbe\u65bd", "pty": "1101"}}]}