{"type": "FeatureCollection", "features": [{"type": "Feature", "geometry": {"type": "Point", "coordinates": [121.40401518386643, 31.238247276908908]}, "properties": {"name": "\u666e\u9640\u533a\u5987\u5973\u513f\u7ae5\u6d3b\u52a8\u6307\u5bfc\u4e2d\u5fc3", "biz": "130403|140800 \u653f\u5e9c\u673a\u6784\u53ca\u793e\u4f1a\u56e2\u4f53;\u793e\u4f1a\u56e2\u4f53;\u5987\u8054|\u79d1\u6559\u6587\u5316\u670d\u52a1;\u6587\u5316\u5bab;\u6587\u5316\u5bab", "pty": "1304"}}, {"type": "Feature", "geometry": {"type": "Point", "coordinates": [121.40401518386643, 31.238247276908908]}, "properties": {"name": "\u666e\u9640\u533a\u5987\u5973\u513f\u7ae5\u6d3b\u52a8\u6307\u5bfc\u4e2d\u5fc3", "biz": "130403|140800 \u653f\u5e9c\u673a\u6784\u53ca\u793e\u4f1a\u56e2\u4f53;\u793e\u4f1a\u56e2\u4f53;\u5987\u8054|\u79d1\u6559\u6587\u5316\u670d\u52a1;\u6587\u5316\u5bab;\u6587\u5316\u5bab", "pty": "1304"}}]}